Metadata-Version: 1.0
Name: python-cuisinelibre
Version: 0.1.1
Summary: Easy-to-use Python API for the cusine-libre.fr cokking website.
Home-page: https://github.com/remaudcorentin-dev/python-cuisinelibre
Author: Corentin Remaud
Author-email: remaudcorentin.dev@gmail.com
License: MIT
Platform: UNKNOWN
